tightbinder/__init__.py
tightbinder/crystal.py
tightbinder/disorder.py
tightbinder/fileparse.py
tightbinder/main.py
tightbinder/models.py
tightbinder/modifiers.py
tightbinder/observables.py
tightbinder/optimize.py
tightbinder/result.py
tightbinder/system.py
tightbinder/topology.py
tightbinder/utils.py
tightbinder-0.2.2.dist-info/licenses/LICENSE
tightbinder-0.2.2.dist-info/METADATA
tightbinder-0.2.2.dist-info/WHEEL
tightbinder-0.2.2.dist-info/top_level.txt
tightbinder-0.2.2.dist-info/RECORD
