Metadata-Version: 2.4
Name: tightbinder
Version: 0.2.2
Summary: Slater-Koster tight-binding library for crystalline and disordered solids
Author: J. J. Palacios
Author-email: "A. J. Uría-Álvarez" <uria@itp.uni-frankfurt.de>
Maintainer-email: "A. J. Uría-Álvarez" <uria@itp.uni-frankfurt.de>
License:                     GNU GENERAL PUBLIC LICENSE
Project-URL: Homepage, https://github.com/alejandrojuria/tightbinder
Project-URL: Bug Reports, https://github.com/alejandrojuria/tightbinder/issues
Keywords: tight-binding,electronic structure,topology,amorphous
Requires-Python: >=3.7
License-File: LICENSE
Requires-Dist: numpy
Requires-Dist: scipy
Requires-Dist: matplotlib
Requires-Dist: vpython
Provides-Extra: tests
Requires-Dist: pytest; extra == "tests"
Provides-Extra: docs
Requires-Dist: sphinx; extra == "docs"
Requires-Dist: pydata-sphinx-theme; extra == "docs"
Requires-Dist: sphinx-autodoc-typehints; extra == "docs"
Requires-Dist: sphinx_rtd_theme; extra == "docs"
Dynamic: license-file
